{
  "ingredients": [
    {
      "name": "Lettuce",
      "season": "All year",
      "price": "1.00",
      "unit": "head",
      "category": "Leafy greens"
    },
    {
      "name": "Carrot",
      "season": "Fall and winter",
      "price": "2.00",
      "unit": "kg",
      "category": "Vegetables"
    },
    {
      "name": "Baby tomato",
      "season": "Late summer and fall",
      "price": "5.00",
      "unit": "kg",
      "category": "Vegetables"
    },
    {
      "name": "Salmon",
      "season": "All year",
      "price": "20.00",
      "unit": "kg",
      "category": "Fish"
    },
    {
      "name": "Parmesan",
      "season": "All year",
      "price": "15.00",
      "unit": "kg",
      "category": "Dairy"
    },
    {
      "name": "Egg",
      "season": "All year",
      "price": "0.20",
      "unit": "unit",
      "category": "Dairy"
    }
  ]
}